csghub_sdk-0.8.2.dist-info/licenses/LICENSE
pycsghub/__init__.py
pycsghub/_token.py
pycsghub/cache.py
pycsghub/cli.py
pycsghub/commit_ops.py
pycsghub/constants.py
pycsghub/csghub_api.py
pycsghub/errors.py
pycsghub/file_download.py
pycsghub/file_upload.py
pycsghub/lfs.py
pycsghub/repository.py
pycsghub/snapshot_download.py
pycsghub/utils.py
pycsghub/__pycache__/__init__.cpython-310.pyc
pycsghub/__pycache__/__init__.cpython-311.pyc
pycsghub/__pycache__/__init__.cpython-312.pyc
pycsghub/__pycache__/__init__.cpython-313.pyc
pycsghub/__pycache__/__init__.cpython-38.pyc
pycsghub/__pycache__/_token.cpython-310.pyc
pycsghub/__pycache__/_token.cpython-311.pyc
pycsghub/__pycache__/_token.cpython-312.pyc
pycsghub/__pycache__/_token.cpython-313.pyc
pycsghub/__pycache__/_token.cpython-38.pyc
pycsghub/__pycache__/cache.cpython-310.pyc
pycsghub/__pycache__/cache.cpython-311.pyc
pycsghub/__pycache__/cache.cpython-312.pyc
pycsghub/__pycache__/cache.cpython-313.pyc
pycsghub/__pycache__/cache.cpython-38.pyc
pycsghub/__pycache__/cli.cpython-310.pyc
pycsghub/__pycache__/cli.cpython-311.pyc
pycsghub/__pycache__/cli.cpython-312.pyc
pycsghub/__pycache__/cli.cpython-313.pyc
pycsghub/__pycache__/cli.cpython-38.pyc
pycsghub/__pycache__/commit_ops.cpython-310.pyc
pycsghub/__pycache__/constants.cpython-310.pyc
pycsghub/__pycache__/constants.cpython-311.pyc
pycsghub/__pycache__/constants.cpython-312.pyc
pycsghub/__pycache__/constants.cpython-313.pyc
pycsghub/__pycache__/constants.cpython-38.pyc
pycsghub/__pycache__/csghub_api.cpython-310.pyc
pycsghub/__pycache__/csghub_api.cpython-311.pyc
pycsghub/__pycache__/csghub_api.cpython-312.pyc
pycsghub/__pycache__/csghub_api.cpython-313.pyc
pycsghub/__pycache__/csghub_api.cpython-38.pyc
pycsghub/__pycache__/errors.cpython-310.pyc
pycsghub/__pycache__/errors.cpython-311.pyc
pycsghub/__pycache__/errors.cpython-312.pyc
pycsghub/__pycache__/errors.cpython-313.pyc
pycsghub/__pycache__/errors.cpython-38.pyc
pycsghub/__pycache__/file_download.cpython-310.pyc
csghub_sdk-0.8.2.dist-info/METADATA
csghub_sdk-0.8.2.dist-info/WHEEL
csghub_sdk-0.8.2.dist-info/entry_points.txt
csghub_sdk-0.8.2.dist-info/top_level.txt
csghub_sdk-0.8.2.dist-info/RECORD
