Metadata-Version: 2.4
Name: csghub-sdk
Version: 0.8.2
Summary: CSGHub SDK for downloading and uploading models, datasets, and spaces
Author-email: opencsg <contact@opencsg.com>
License: Apache-2.0
Project-URL: Homepage, https://github.com/OpenCSGs/csghub-sdk
Project-URL: Repository, https://github.com/OpenCSGs/csghub-sdk
Project-URL: Issues, https://github.com/OpenCSGs/csghub-sdk
Keywords: ai,machine-learning,models,datasets,huggingface
Classifier: Development Status :: 4 - Beta
Classifier: Intended Audience :: Developers
Classifier: License :: OSI Approved :: Apache Software License
Classifier: Operating System :: OS Independent
Classifier: Programming Language :: Python :: 3
Classifier: Programming Language :: Python :: 3.10
Classifier: Programming Language :: Python :: 3.11
Classifier: Programming Language :: Python :: 3.12
Classifier: Programming Language :: Python :: 3.13
Classifier: Programming Language :: Python :: 3.14
Classifier: Topic :: Scientific/Engineering :: Artificial Intelligence
Classifier: Topic :: Software Development :: Libraries :: Python Modules
Requires-Python: <=3.14,>3.9
License-File: LICENSE
Requires-Dist: requests
Requires-Dist: typer
Requires-Dist: typing-extensions
Requires-Dist: huggingface_hub>=1.2.0
Requires-Dist: python-dotenv
Provides-Extra: train
Requires-Dist: torch; extra == "train"
Requires-Dist: transformers==5.0.0rc0; extra == "train"
Requires-Dist: datasets>=2.20.0; extra == "train"
Requires-Dist: accelerate>=1.1.0; extra == "train"
Dynamic: license-file
